noora/__init__.py
noora/mynoora_cli.py
noora/myproject.json
noora/connectors/Connectable.py
noora/connectors/ConnectionExecutor.py
noora/connectors/Connector.py
noora/connectors/MssqlConnector.py
noora/connectors/MysqlConnector.py
noora/connectors/MysqlConnectorStub.py
noora/connectors/PGSQLConnector.py
noora/connectors/__init__.py
noora/exceptions/ConnectorException.py
noora/exceptions/IOException.py
noora/exceptions/__init__.py
noora/exceptions/plugins/BlockedHostException.py
noora/exceptions/plugins/InvalidEnvironmentException.py
noora/exceptions/plugins/InvalidVersionException.py
noora/exceptions/plugins/PluginException.py
noora/exceptions/plugins/UnknownVersionException.py
noora/exceptions/plugins/__init__.py
noora/io/File.py
noora/io/FileExtensionFilter.py
noora/io/FileFilter.py
noora/io/FileFolderFilter.py
noora/io/Files.py
noora/io/Filterable.py
noora/io/Filters.py
noora/io/__init__.py
noora/plugins/Fail.py
noora/plugins/Plugin.py
noora/plugins/__init__.py
noora/plugins/mssql/MssqlPlugin.py
noora/plugins/mssql/__init__.py
noora/plugins/mssql/create/CreatePlugin.py
noora/plugins/mssql/create/__init__.py
noora/plugins/mssql/drop/DropPlugin.py
noora/plugins/mssql/drop/__init__.py
noora/plugins/mssql/drop/cst/drop_foreign_keys.sql
noora/plugins/mssql/drop/fct/drop_functions.sql
noora/plugins/mssql/drop/seq/drop_sequences.sql
noora/plugins/mssql/drop/tab/drop_tables.sql
noora/plugins/mssql/generate/GeneratePlugin.py
noora/plugins/mssql/generate/__init__.py
noora/plugins/mssql/generate/templates/myproject.json
noora/plugins/mssql/generate/templates/fct/app_prop.sql
noora/plugins/mssql/generate/templates/idx/application_properties.sql
noora/plugins/mssql/generate/templates/tab/application_properties.sql
noora/plugins/mssql/generate/templates/trg/application_properties_biu.sql
noora/plugins/mssql/recreate/RecreatePlugin.py
noora/plugins/mssql/recreate/__init__.py
noora/plugins/mssql/update/UpdatePlugin.py
noora/plugins/mssql/update/__init__.py
noora-1.2.5.dist-info/AUTHORS
noora-1.2.5.dist-info/LICENSE
noora-1.2.5.dist-info/METADATA
noora-1.2.5.dist-info/WHEEL
noora-1.2.5.dist-info/entry_points.txt
noora-1.2.5.dist-info/top_level.txt
noora-1.2.5.dist-info/RECORD
