Metadata-Version: 2.1
Name: noora
Version: 1.2.5
Summary: NoOra a database deployment tool.
Home-page: https://github.com/janripke/noora
Author: Jan Ripke
Author-email: janripke@gmail.com
Maintainer: Jan Ripke
Maintainer-email: janripke@gmail.com
License: Apache License 2.0
Keywords: development database
Classifier: Development Status :: 5 - Production/Stable
Classifier: Intended Audience :: Developers
Classifier: Topic :: Database :: Front-Ends
Classifier: License :: OSI Approved :: Apache Software License
Classifier: Programming Language :: Python :: 2
Classifier: Programming Language :: Python :: 2.7
License-File: LICENSE
License-File: AUTHORS
Requires-Dist: six
Requires-Dist: click
Requires-Dist: fire
